kubeai/__init__.py
kubeai/api.py
kubeai/elastic.py
kubeai/evaluate/__init__.py
kubeai/evaluate/evaluator.py
kubeai/evaluate/mysql_handler.py
kubeai-0.1.0.dist-info/METADATA
kubeai-0.1.0.dist-info/WHEEL
kubeai-0.1.0.dist-info/top_level.txt
kubeai-0.1.0.dist-info/RECORD
