Metadata-Version: 2.1
Name: kubeai
Version: 0.1.0
Summary: Python SDK of Alibaba Cloud KubeAI
Home-page: UNKNOWN
Author: AlanFok
Author-email: huozhixin.hzx@alibaba-inc.com
License: UNKNOWN
Platform: UNKNOWN
Requires-Dist: pymysql
